mabledsocli/__init__.py
mabledsocli/__main__.py
mabledsocli/aws_utils.py
mabledsocli/cli.py
mabledsocli/cli_constants.py
mabledsocli/cli_utils.py
mabledsocli/click_extend.py
mabledsocli/config.py
mabledsocli/constants.py
mabledsocli/contexts.py
mabledsocli/dict_utils.py
mabledsocli/editor.py
mabledsocli/enum_utils.py
mabledsocli/exceptions.py
mabledsocli/file_utils.py
mabledsocli/local_utils.py
mabledsocli/logger.py
mabledsocli/network_utils.py
mabledsocli/networks.py
mabledsocli/package.json
mabledsocli/pager.py
mabledsocli/parameters.py
mabledsocli/providers.py
mabledsocli/secrets.py
mabledsocli/settings.py
mabledsocli/stages.py
mabledsocli/templates.py
mabledsocli/version.py
mabledsocli/provider/__init__.py
mabledsocli/provider/parameter/__init__.py
mabledsocli/provider/parameter/aws/__init__.py
mabledsocli/provider/parameter/aws/ssm/__init__.py
mabledsocli/provider/parameter/aws/ssm/v1/__init__.py
mabledsocli/provider/parameter/aws/ssm/v1/main.py
mabledsocli/provider/parameter/local/__init__.py
mabledsocli/provider/parameter/local/v1/__init__.py
mabledsocli/provider/parameter/local/v1/main.py
mabledsocli/provider/secret/__init__.py
mabledsocli/provider/secret/aws/__init__.py
mabledsocli/provider/secret/aws/ssm/__init__.py
mabledsocli/provider/secret/aws/ssm/v1/__init__.py
mabledsocli/provider/secret/aws/ssm/v1/main.py
mabledsocli/provider/template/__init__.py
mabledsocli/provider/template/aws/__init__.py
mabledsocli/provider/template/aws/ssm/__init__.py
mabledsocli/provider/template/aws/ssm/v1/__init__.py
mabledsocli/provider/template/aws/ssm/v1/main.py
mabledsocli/provider/template/local/__init__.py
mabledsocli/provider/template/local/v1/__init__.py
mabledsocli/provider/template/local/v1/main.py
mabledsocli-1.0.83.dist-info/LICENSE.md
mabledsocli-1.0.83.dist-info/METADATA
mabledsocli-1.0.83.dist-info/WHEEL
mabledsocli-1.0.83.dist-info/entry_points.txt
mabledsocli-1.0.83.dist-info/top_level.txt
mabledsocli-1.0.83.dist-info/RECORD
