Metadata-Version: 2.1
Name: mabledsocli
Version: 1.0.83
Summary: Mable DSO CLI
Home-page: https://github.com/bettercaring/mabledsocli
Author: Ramtin Kazemi
Author-email: ramtin.kazemi@mable.com.au
License: GPLV3
Project-URL: Documentation, https://github.com/bettercaring/mabledsocli
Project-URL: Source, https://github.com/bettercaring/mabledsocli
Platform: UNKNOWN
Classifier: License :: OSI Approved :: GNU General Public License v3 (GPLv3)
Classifier: Programming Language :: Python
Classifier: Programming Language :: Python :: 3
Classifier: Programming Language :: Python :: 3.9
Classifier: Programming Language :: Python :: Implementation :: CPython
Classifier: Programming Language :: Python :: Implementation :: PyPy
Requires-Python: >=3.0
Requires-Dist: pyyaml
Requires-Dist: pyjson
Requires-Dist: boto
Requires-Dist: boto3
Requires-Dist: click
Requires-Dist: click-params
Requires-Dist: stdiomask
Requires-Dist: requests
Requires-Dist: setuptools
Requires-Dist: wheel
Requires-Dist: jinja2
Requires-Dist: jmespath
Requires-Dist: colorama
Requires-Dist: coloredlogs
Requires-Dist: winreg ; sys_platform == "Windows"
